indexage/__init__.py
indexage/__main__.py
indexage/assets.py
indexage/lib.py
indexage-1.1.0.dist-info/licenses/LICENSE
indexage-1.1.0.dist-info/METADATA
indexage-1.1.0.dist-info/WHEEL
indexage-1.1.0.dist-info/top_level.txt
indexage-1.1.0.dist-info/RECORD
